tiff_stack_crop_tool/__init__.py
tiff_stack_crop_tool/cli.py
tiff_stack_crop_tool/selectinwindow.py
tiff_stack_crop_tool/tiff_stack_crop_tool.py
tiff_stack_crop_tool/zStackUtils.py
tiff_stack_crop_tool-0.6.dist-info/AUTHORS.rst
tiff_stack_crop_tool-0.6.dist-info/LICENSE
tiff_stack_crop_tool-0.6.dist-info/METADATA
tiff_stack_crop_tool-0.6.dist-info/WHEEL
tiff_stack_crop_tool-0.6.dist-info/entry_points.txt
tiff_stack_crop_tool-0.6.dist-info/top_level.txt
tiff_stack_crop_tool-0.6.dist-info/RECORD
