Metadata-Version: 2.1
Name: tiff-stack-crop-tool
Version: 0.6
Summary: Utility for cropping tiff stacks in 3D.
Home-page: https://github.com/JulianPitney/tiff_stack_crop_tool
Author: Julian Pitney
Author-email: julianpitney@Gmail.com
License: MIT license
Keywords: tiff_stack_crop_tool
Platform: UNKNOWN
Classifier: Development Status :: 2 - Pre-Alpha
Classifier: Intended Audience :: Developers
Classifier: License :: OSI Approved :: MIT License
Classifier: Natural Language :: English
Classifier: Programming Language :: Python :: 3
Classifier: Programming Language :: Python :: 3.5
Classifier: Programming Language :: Python :: 3.6
Classifier: Programming Language :: Python :: 3.7
Classifier: Programming Language :: Python :: 3.8
Requires-Python: >=3.5
Requires-Dist: opencv-python (==3.2.0.6)
Requires-Dist: tiffile
Requires-Dist: imagecodecs
Requires-Dist: numpy (==1.19.2)
Requires-Dist: pywin32
